monist/__init__.py
monist/monist.py
monist-0.1.0.dist-info/LICENSE
monist-0.1.0.dist-info/WHEEL
monist-0.1.0.dist-info/METADATA
monist-0.1.0.dist-info/RECORD
