Metadata-Version: 2.1
Name: monist
Version: 0.1.0
Summary: Simple singleton to share variables across modules
Home-page: https://github.com/datagazing/monist
Author: Brendan Strejcek
Author-email: brendan@datagazing.com
Requires-Python: >=3.7
Classifier: License :: OSI Approved :: MIT License
